{
  "novelWriter.tagsIndex": {
    "dataanalysis": {"name": "DataAnalysis", "display": "DataAnalysis", "handle": "030e3a81d9546", "heading": "T0001", "class": "WORLD"},
    "onion": {"name": "Onion", "display": "Onion", "handle": "0696d8dec917d", "heading": "T0001", "class": "CHARACTER"},
    "correlations": {"name": "Correlations", "display": "Correlations", "handle": "7d494e6193cc2", "heading": "T0001", "class": "WORLD"},
    "flow": {"name": "Flow", "display": "Flow", "handle": "f10aa2954e380", "heading": "T0001", "class": "PLOT"}
  },
  "novelWriter.itemIndex": {
    "030e3a81d9546": {
      "T0001": {
        "meta": {"level": "H1", "title": "Main Location", "line": 1, "tag": "dataanalysis", "counts": [13, 2, 0]},
        "summary": "A short description."
      }
    },
    "0696d8dec917d": {
      "T0001": {
        "meta": {"level": "H1", "title": "Onion", "line": 1, "tag": "onion", "counts": [5, 1, 0]},
        "summary": "A short description."
      }
    },
    "078d385b301fd": {
      "T0001": {
        "meta": {"level": "H3", "title": "Scene 2.3", "line": 1, "tag": "", "counts": [9, 2, 0]},
        "summary": "Summary of the scene."
      }
    },
    "07932c781671c": {
      "T0001": {
        "meta": {"level": "H2", "title": "Introduction", "line": 1, "tag": "", "counts": [12, 1, 0]},
        "summary": "Jets, their breakup, introduction of bubbles, jets with cavitation bubbles a twist on effervescent atomization"
      }
    },
    "0aa0458695246": {
      "T0001": {
        "meta": {"level": "H3", "title": "Scene 2.1", "line": 1, "tag": "", "counts": [9, 2, 0]},
        "summary": "Summary of the scene."
      }
    },
    "1fce19a90f5cc": {
      "T0001": {
        "meta": {"level": "H3", "title": "Jet dynamics at the exit", "line": 1, "tag": "", "counts": [24, 5, 0]},
        "summary": "Summary of the scene."
      }
    },
    "2a43153953c4a": {
      "T0001": {
        "meta": {"level": "H3", "title": "Cavitation cloud in the manifold", "line": 1, "tag": "", "counts": [1011, 150, 5]},
        "summary": "We discuss the formation, characteristics, and parameter variations of the acoustic cavitation cloud in the manifold."
      }
    },
    "2da031468c637": {
      "T0001": {
        "meta": {"level": "H2", "title": "Chapter 2", "line": 1, "tag": "", "counts": [9, 2, 0]},
        "summary": "Summary of the chapter."
      }
    },
    "4cee2d94c8efd": {
      "T0001": {
        "meta": {"level": "H1", "title": "Plain jet disintegration induced by acoustic cavitation in the manifold", "line": 7, "tag": "", "counts": [101, 15, 2]}
      }
    },
    "526204300aafd": {
      "T0001": {
        "meta": {"level": "H3", "title": "Jet breakup mechanism", "line": 1, "tag": "", "counts": [21, 3, 0]},
        "summary": "Summary of the scene."
      }
    },
    "6bece7ec22439": {
      "T0001": {
        "meta": {"level": "H1", "title": "Sheet", "line": 1, "tag": "", "counts": [5, 1, 0]}
      }
    },
    "7d494e6193cc2": {
      "T0001": {
        "meta": {"level": "H1", "title": "Correlations", "line": 1, "tag": "correlations", "counts": [12, 1, 0]},
        "summary": "A short description."
      }
    },
    "83b05b87e3e61": {
      "T0001": {
        "meta": {"level": "H3", "title": "Jet breakup in the presence of bubbles", "line": 1, "tag": "", "counts": [38, 7, 0]},
        "summary": "Summary of the scene."
      }
    },
    "870371b4ff8ea": {
      "T0001": {
        "meta": {"level": "H1", "title": "Analytical", "line": 1, "tag": "", "counts": [10, 1, 0]}
      }
    },
    "87e9be743c41b": {
      "T0001": {
        "meta": {"level": "H3", "title": "Scene 4.3", "line": 1, "tag": "", "counts": [9, 2, 0]},
        "summary": "Summary of the scene."
      }
    },
    "88e8b43f7627e": {
      "T0001": {
        "meta": {"level": "H1", "title": "Experiments", "line": 1, "tag": "", "counts": [11, 1, 0]}
      },
      "T0002": {
        "meta": {"level": "H2", "title": "Bubble size measurements", "line": 3, "tag": "", "counts": [24, 3, 0]}
      }
    },
    "9591325246e05": {
      "T0001": {
        "meta": {"level": "H3", "title": "Plain jet breakup", "line": 1, "tag": "", "counts": [17, 3, 0]},
        "summary": "General features of jet breakup"
      }
    },
    "9a1f3a1b8442e": {
      "T0001": {
        "meta": {"level": "H1", "title": "Simulation", "line": 1, "tag": "", "counts": [10, 1, 0]}
      }
    },
    "a1176d904164f": {
      "T0001": {
        "meta": {"level": "H2", "title": "Chapter 3", "line": 1, "tag": "", "counts": [9, 2, 0]},
        "summary": "Summary of the chapter."
      }
    },
    "a7d819db24d21": {
      "T0001": {
        "meta": {"level": "H3", "title": "Acoustic cavitation and cavitation bubbles", "line": 1, "tag": "", "counts": [42, 5, 0]},
        "summary": "Summary of the scene."
      }
    },
    "ab53e3224d9c6": {
      "T0001": {
        "meta": {"level": "H1", "title": "list", "line": 1, "tag": "", "counts": [4, 1, 0]}
      }
    },
    "b2da32b9068e8": {
      "T0001": {
        "meta": {"level": "H3", "title": "Scene 4.2", "line": 1, "tag": "", "counts": [9, 2, 0]},
        "summary": "Summary of the scene."
      }
    },
    "c8e2a6317e4df": {
      "T0001": {
        "meta": {"level": "H3", "title": "Scene 2.2", "line": 1, "tag": "", "counts": [9, 2, 0]},
        "summary": "Summary of the scene."
      }
    },
    "cc18326314820": {
      "T0001": {
        "meta": {"level": "H3", "title": "Scene 4.1", "line": 1, "tag": "", "counts": [9, 2, 0]},
        "summary": "Summary of the scene."
      }
    },
    "cc834cdbe1117": {
      "T0001": {
        "meta": {"level": "H1", "title": "Ligaments", "line": 1, "tag": "", "counts": [9, 1, 0]}
      }
    },
    "dac686d435a9b": {
      "T0001": {
        "meta": {"level": "H2", "title": "Chapter 4", "line": 1, "tag": "", "counts": [9, 2, 0]},
        "summary": "Summary of the chapter."
      }
    },
    "eceae29d942fa": {
      "T0001": {
        "meta": {"level": "H1", "title": "Droplets", "line": 1, "tag": "", "counts": [8, 1, 0]}
      }
    },
    "f10aa2954e380": {
      "T0001": {
        "meta": {"level": "H1", "title": "Main Plot", "line": 1, "tag": "flow", "counts": [9, 2, 0]},
        "summary": "A short description."
      }
    },
    "412dbe83812b8": {
      "T0001": {
        "meta": {"level": "H3", "title": "Cavitation effects", "line": 1, "tag": "", "counts": [18, 2, 0]}
      }
    },
    "e94c8a256c622": {
      "T0001": {
        "meta": {"level": "H3", "title": "Spray cone angle", "line": 1, "tag": "", "counts": [16, 3, 0]}
      }
    },
    "7cade71fc6be7": {
      "T0001": {
        "meta": {"level": "H3", "title": "Radial evolution of structures", "line": 1, "tag": "", "counts": [30, 4, 0]}
      }
    },
    "1a1272a453850": {
      "T0001": {
        "meta": {"level": "H3", "title": "Breakup length", "line": 1, "tag": "", "counts": [14, 2, 0]}
      }
    },
    "fc5ed01235846": {
      "T0001": {
        "meta": {"level": "H3", "title": "Droplet size distribution", "line": 1, "tag": "", "counts": [25, 3, 0]}
      }
    },
    "a96fabdd06480": {
      "T0001": {
        "meta": {"level": "H3", "title": "Spray unsteadiness", "line": 1, "tag": "", "counts": [18, 2, 0]}
      }
    },
    "8f936abf352d1": {
      "T0001": {
        "meta": {"level": "H3", "title": "POD modes", "line": 1, "tag": "", "counts": [9, 2, 0]}
      }
    },
    "ce564d8aca4f3": {
      "T0001": {
        "meta": {"level": "H3", "title": "Droplet velocity distribution", "line": 1, "tag": "", "counts": [29, 3, 0]}
      }
    },
    "a9c6f85051d24": {
      "T0000": {
        "meta": {"level": "H0", "title": "", "line": 0, "tag": "", "counts": [0, 0, 0]}
      }
    },
    "59d1fb06ae3c7": {
      "T0001": {
        "meta": {"level": "H2", "title": "Abstract", "line": 1, "tag": "", "counts": [100, 13, 1]}
      }
    },
    "5ac0ed7209b7d": {
      "T0001": {
        "meta": {"level": "H3", "title": "archive", "line": 1, "tag": "", "counts": [7, 1, 0]}
      }
    },
    "426477502a0ff": {
      "T0001": {
        "meta": {"level": "H3", "title": "Bubble evolution in the jet", "line": 1, "tag": "", "counts": [334, 58, 1]},
        "summary": "Description of bubbles convecting with the jet through the pressure drop"
      }
    }
  }
}
